p115client/__init__.py
p115client/client.py
p115client/const.py
p115client/exception.py
p115client/py.typed
p115client/tool/__init__.py
p115client/tool/attr.py
p115client/tool/auth.py
p115client/tool/download.py
p115client/tool/edit.py
p115client/tool/export_dir.py
p115client/tool/fs_files.py
p115client/tool/history.py
p115client/tool/iterdir.py
p115client/tool/life.py
p115client/tool/offline.py
p115client/tool/pool.py
p115client/tool/updatedb.py
p115client/tool/upload.py
p115client/tool/xys.py
p115client/type.py
p115client/util.py
p115client-0.0.7.8.dist-info/METADATA
p115client-0.0.7.8.dist-info/WHEEL
p115client-0.0.7.8.dist-info/licenses/LICENSE
p115client-0.0.7.8.dist-info/RECORD
