Metadata-Version: 2.4
Name: p115client
Version: 0.0.7.8
Summary: Python 115 webdisk client.
License: MIT
License-File: LICENSE
Keywords: 115,webdisk,client
Author: ChenyangGao
Author-email: wosiwujm@gmail.com
Requires-Python: >=3.12,<4.0
Classifier: Development Status :: 4 - Beta
Classifier: Intended Audience :: Developers
Classifier: License :: OSI Approved :: MIT License
Classifier: Operating System :: OS Independent
Classifier: Programming Language :: Python
Classifier: Programming Language :: Python :: 3
Classifier: Programming Language :: Python :: 3.12
Classifier: Programming Language :: Python :: 3.13
Classifier: Programming Language :: Python :: 3.14
Classifier: Programming Language :: Python :: 3 :: Only
Classifier: Topic :: Software Development
Classifier: Topic :: Software Development :: Libraries
Classifier: Topic :: Software Development :: Libraries :: Python Modules
Requires-Dist: ed2k (>=0.0.2.2)
Requires-Dist: errno2 (>=0.0.5)
Requires-Dist: http_client_request (>=0.1.1)
Requires-Dist: http_response (>=0.0.9)
Requires-Dist: httpcore_request (>=0.0.6.4)
Requires-Dist: integer_tool (>=0.0.6)
Requires-Dist: iter_collect (>=0.0.6)
Requires-Dist: iterdir (>=0.0.10)
Requires-Dist: orjson
Requires-Dist: p115cipher (>=0.0.4)
Requires-Dist: p115oss (>=0.0.9)
Requires-Dist: p115pickcode (>=0.0.5)
Requires-Dist: posixpatht (>=0.0.3)
Requires-Dist: python-argtools (>=0.0.1)
Requires-Dist: python-asynctools (>=0.1.3)
Requires-Dist: python-concurrenttools (>=0.1.4)
Requires-Dist: python-cookietools (>=0.1.4)
Requires-Dist: python-dictattr (>=0.0.4)
Requires-Dist: python-dicttools (>=0.0.4)
Requires-Dist: python-encode_uri (>=0.0.3)
Requires-Dist: python-ensure (>=0.0.1)
Requires-Dist: python-filewrap (>=0.2.9)
Requires-Dist: python-hashtools (>=0.0.6)
Requires-Dist: python-http_request (>=0.1.4)
Requires-Dist: python-httpfile (>=0.0.5.4)
Requires-Dist: python-iterutils (>=0.2.10)
Requires-Dist: python-property (>=0.0.3)
Requires-Dist: python-startfile (>=0.0.2)
Requires-Dist: python-temporary (>=0.0.1)
Requires-Dist: python-undefined (>=0.0.3)
Requires-Dist: qrcode
Requires-Dist: sqlitetools (>=0.0.5)
Requires-Dist: yarl
Project-URL: Documentation, https://p115client.readthedocs.io
Project-URL: Homepage, https://github.com/ChenyangGao/p115client
Project-URL: Repository, https://github.com/ChenyangGao/p115client
